arcos4py/__init__.py
arcos4py/_arcos4py.py
arcos4py/plotting/__init__.py
arcos4py/plotting/_plotting.py
arcos4py/tools/__init__.py
arcos4py/tools/_arcos4py_deprecation.py
arcos4py/tools/_binarize_detrend.py
arcos4py/tools/_cleandata.py
arcos4py/tools/_detect_events.py
arcos4py/tools/_filter_events.py
arcos4py/tools/_linking.py
arcos4py/tools/_stats.py
arcos4py/validation/__init__.py
arcos4py/validation/_bootstrapping.py
arcos4py/validation/_resampling.py
arcos4py-0.3.3.dist-info/METADATA
arcos4py-0.3.3.dist-info/WHEEL
arcos4py-0.3.3.dist-info/licenses/LICENSE
arcos4py-0.3.3.dist-info/RECORD
