Metadata-Version: 2.4
Name: arcos4py
Version: 0.3.3
Summary: A python package to detect collective spatio-temporal phenomena.
License: MIT
License-File: LICENSE
Author: Benjamin Graedel
Author-email: benjamin.graedel@unibe.ch
Requires-Python: >=3.10
Classifier: License :: OSI Approved :: MIT License
Classifier: Natural Language :: English
Classifier: Programming Language :: Python :: 3.10
Classifier: Programming Language :: Python :: 3.11
Classifier: Programming Language :: Python :: 3.12
Classifier: Programming Language :: Python :: 3.13
Provides-Extra: dev
Provides-Extra: doc
Provides-Extra: test
Requires-Dist: PyYAML (>=6.0) ; extra == "test"
Requires-Dist: black (>=24.1.1) ; extra == "test"
Requires-Dist: bump2version (>=1.0.1) ; extra == "dev"
Requires-Dist: flake8 (>=3.9.2) ; extra == "test"
Requires-Dist: flake8-docstrings (>=1.6.0) ; extra == "test"
Requires-Dist: isort (>=5.8.0) ; extra == "test"
Requires-Dist: joblib (>=1.2.0)
Requires-Dist: kneed (>=0.7.0)
Requires-Dist: matplotlib (>=3.6)
Requires-Dist: mkdocs (>=1.3.0) ; extra == "doc"
Requires-Dist: mkdocs-autorefs (>=0.5.0) ; extra == "doc"
Requires-Dist: mkdocs-include-markdown-plugin (>=3.3.0) ; extra == "doc"
Requires-Dist: mkdocs-material (>=9.5.9) ; extra == "doc"
Requires-Dist: mkdocs-material-extensions (>=1.0.3) ; extra == "doc"
Requires-Dist: mkdocstrings-python (>=1.2.1) ; extra == "doc"
Requires-Dist: mypy (>=0.981) ; extra == "test"
Requires-Dist: numba (>=0.60.0)
Requires-Dist: numpy (>=1.23)
Requires-Dist: pandas (>=1.4.0)
Requires-Dist: pot (>=0.9.4)
Requires-Dist: pre-commit (>=2.12.0) ; extra == "dev"
Requires-Dist: pytest (>=8.0.0) ; extra == "test"
Requires-Dist: pytest-cov (>=2.12.0) ; extra == "test"
Requires-Dist: scikit-image (>=0.22.0)
Requires-Dist: scikit-learn (>=1.3.0)
Requires-Dist: scipy (>=1.9)
Requires-Dist: seaborn (>=0.13.2)
Requires-Dist: toml (>=0.10.2) ; extra == "dev"
Requires-Dist: tox (>=3.20.1) ; extra == "dev"
Requires-Dist: tqdm (>=4.64.1)
Requires-Dist: twine (>=3.3.0) ; extra == "dev"
Requires-Dist: virtualenv (>=20.2.2) ; extra == "dev"
Project-URL: Homepage, https://github.com/pertzlab/arcos4py
